loggerbyclass.py
setup.py
loggerbyclass.egg-info/PKG-INFO
loggerbyclass.egg-info/SOURCES.txt
loggerbyclass.egg-info/dependency_links.txt
loggerbyclass.egg-info/top_level.txt