Metadata-Version: 1.1
Name: loggerbyclass
Version: 0.2.0
Summary: 
